gbm_org_analysis/__init__.py
gbm_org_analysis/extract.py
gbm_org_analysis/figs.py
gbm_org_analysis/integrate.py
gbm_org_analysis/stats.py
gbm_org_analysis-3.0.0.dist-info/LICENSE
gbm_org_analysis-3.0.0.dist-info/METADATA
gbm_org_analysis-3.0.0.dist-info/WHEEL
gbm_org_analysis-3.0.0.dist-info/top_level.txt
gbm_org_analysis-3.0.0.dist-info/RECORD
