Metadata-Version: 2.1
Name: gbm-org-analysis
Version: 3.0.0
Summary: Extracts and analyzes GBM-organoid data exported from Imaris
Home-page: https://github.com/rybinmj/gbm_org_analysis
Author: Matt Rybin
Author-email: mxr2011@miami.edu
License: UNKNOWN
Platform: UNKNOWN
Classifier: Programming Language :: Python :: 3
Classifier: License :: OSI Approved :: GNU General Public License v3 or later (GPLv3+)
Classifier: Operating System :: OS Independent
Requires-Python: >=3.6
Requires-Dist: pandas
Requires-Dist: statistics
Requires-Dist: matplotlib
Requires-Dist: seaborn
Requires-Dist: scipy
Requires-Dist: statsmodels
Requires-Dist: openpyxl
